INSTALL.rst
LICENSE
MANIFEST.in
README.rst
VERSION
requirements.txt
setup.py
tasks.py
src/mommys_boy/__init__.py
src/mommys_boy/__main__.py
src/mommys_boy/__meta__.py
src/mommys_boy/base.py
src/mommys_boy.egg-info/PKG-INFO
src/mommys_boy.egg-info/SOURCES.txt
src/mommys_boy.egg-info/dependency_links.txt
src/mommys_boy.egg-info/not-zip-safe
src/mommys_boy.egg-info/requires.txt
src/mommys_boy.egg-info/top_level.txt
src/mommys_boy/tests/__init__.py
src/mommys_boy/tests/__main__.py
src/mommys_boy/tests/test_documentation.py
src/mommys_boy/tests/test_mommys_boy.py
src/mommys_boy/tests/app/__init__.py
src/mommys_boy/tests/app/admin.py
src/mommys_boy/tests/app/apps.py
src/mommys_boy/tests/app/models.py
src/mommys_boy/tests/app/views.py
src/mommys_boy/tests/app/migrations/0001_initial.py
src/mommys_boy/tests/app/migrations/__init__.py
src/mommys_boy/tests/site/__init__.py
src/mommys_boy/tests/site/settings.py
src/mommys_boy/tests/site/urls.py
src/mommys_boy/tests/site/wsgi.py